forumPackage/Content/post.py
forumPackage/Content/topic.py
forumPackage/Person/administrator.py
forumPackage/Person/user.py
forumPackage-0.4.dist-info/LICENSE.txt
forumPackage-0.4.dist-info/METADATA
forumPackage-0.4.dist-info/WHEEL
forumPackage-0.4.dist-info/top_level.txt
forumPackage-0.4.dist-info/RECORD
