Metadata-Version: 2.1
Name: forumPackage
Version: 0.4
Summary: A python package about forum
Home-page: https://github.com/madison13g/Group-8-Step3
Author: Amethyst He
Author-email: hejinghongyue@outlook.com
License: MIT
Platform: UNKNOWN
License-File: LICENSE.txt
